cityblocks/__init__.py
cityblocks/_core.py
cityblocks/cli.py
cityblocks/tile_1_wgs84_51_52_53.gpkg
cityblocks/tile_2_wgs84_54_55_56.gpkg
cityblocks/tile_3_wgs84_57.gpkg
cityblocks/tile_4_wgs84_58.gpkg
cityblocks/tile_5_wgs84_59.gpkg
cityblocks/tile_6_wgs84_60.gpkg
cityblocks/tile_template_wgs84__raster.gpkg
cityblocks-0.0.2.dist-info/LICENSE
cityblocks-0.0.2.dist-info/METADATA
cityblocks-0.0.2.dist-info/WHEEL
cityblocks-0.0.2.dist-info/entry_points.txt
cityblocks-0.0.2.dist-info/top_level.txt
cityblocks-0.0.2.dist-info/RECORD
