Metadata-Version: 2.1
Name: cityblocks
Version: 0.0.2
Summary: Python workflow to generate LCZ tiles for rendering in 3D in QGIS 
Author-email: Peter Kalverla <p.kalverla@esciencecenter.nl>, Maurice de Kleijn <m.dekleijn@esciencecenter.nl>
License-File: LICENSE
Requires-Dist: geopandas
Requires-Dist: numpy
Requires-Dist: rasterio
Requires-Dist: shapely
Requires-Dist: click
